randexpy/__init__.py
randexpy/exceptions.py
randexpy/executor.py
randexpy/result.py
tests/__init__.py
tests/test_executor.py
tests/test_result.py
randexcpy-0.1.0.dist-info/LICENSE
randexcpy-0.1.0.dist-info/METADATA
randexcpy-0.1.0.dist-info/WHEEL
randexcpy-0.1.0.dist-info/top_level.txt
randexcpy-0.1.0.dist-info/RECORD
