Metadata-Version: 2.1
Name: randexcpy
Version: 0.1.0
Summary: A library for executing actions at random times within a specified duration.
Home-page: https://github.com/copleftdev/randexcpy
Author: Don Johnson
Author-email: dj@codetestcode.io
Project-URL: Bug Tracker, https://github.com/copyleftdev/randexcpy/issues
Classifier: Programming Language :: Python :: 3
Classifier: License :: OSI Approved :: MIT License
Classifier: Operating System :: OS Independent
Requires-Python: >=3.8
License-File: LICENSE
